MANIFEST.in
README
setup.cfg
setup.py
usb1208fs/.DS_Store
usb1208fs/__init__.pyc
usb1208fs/c1208fs.pxd
usb1208fs/pmd.c
usb1208fs/pmd.h
usb1208fs/usb-1208FS.c
usb1208fs/usb-1208FS.h
usb1208fs/usb1208fs.c
usb1208fs/usb1208fs.pyx
usb1208fs.egg-info/PKG-INFO
usb1208fs.egg-info/SOURCES.txt
usb1208fs.egg-info/dependency_links.txt
usb1208fs.egg-info/not-zip-safe
usb1208fs.egg-info/requires.txt
usb1208fs.egg-info/top_level.txt
usb1208fs/lib.linux-x86_64-2.7/usb1208fs/__init__.py