Metadata-Version: 1.1
Name: usb1208fs
Version: 0.1.4
Summary: Python drivers for Measurement Computing USB1208FS on linux
Home-page: https://github.com/Flasew/pyusb1208fs
Author: Weiyang Wang
Author-email: wew168@ucsd.edu
License: UNKNOWN
Platform: linux
Classifier: Development Status :: 5 - Production/Stable
Classifier: Environment :: Console
Classifier: Intended Audience :: Science/Research
Classifier: License :: OSI Approved :: GNU Lesser General Public License v2 or later (LGPLv2+)
Classifier: Natural Language :: English
Classifier: Operating System :: POSIX :: Linux
Classifier: Programming Language :: C
Classifier: Programming Language :: Cython
Classifier: Programming Language :: Python :: 2.7
Classifier: Topic :: Scientific/Engineering
